FIFO_SynthesisOptimised.v
`timescale 1ns/1ps

//ACTIVE-LOW RESET - FIFO HEIGHT >= 4

module FIFO
#(parameter WIDTH=16, 
parameter HEIGHT=16)
(input rst, 
input rclk, 
input wclk,
input wEn, 
input rEn, 
input wire [WIDTH-1:0] datIn,
output reg [WIDTH-1:0] datOut,
output reg empty,
output reg full);

    localparam pSize = $clog2(HEIGHT);
    reg [WIDTH-1:0] mem[0:HEIGHT-1];

//rclk domain
    //Read Pointers
    reg [pSize:0] rdptr_bin;
    wire [pSize:0] rdptr_bin_next = rdptr_bin + rdvalid;
    wire [pSize:0] rdptr_grey_next = rdptr_bin_next  ^ (rdptr_bin_next >> 1);
    reg [pSize:0] rdptr_grey;
    
    //Write Syncs
    reg [pSize:0] wrptr_sync1;
    reg [pSize:0] wrptr_sync2;
    
//wclk domain
    //Write Pointers
    reg [pSize:0] wrptr_bin;
    wire [pSize:0] wrptr_bin_next = wrptr_bin + wrvalid;
    wire [pSize:0] wrptr_grey_next = wrptr_bin_next  ^ (wrptr_bin_next >> 1);
    reg [pSize:0] wrptr_grey;

    //Read Syncs
    reg [pSize:0] rdptr_sync1;
    reg [pSize:0] rdptr_sync2;

//Validity
    wire rdvalid = rEn && !empty;
    wire wrvalid = wEn && !full;

//Read Clock Behaviour
    always@(posedge rclk or negedge rst) begin
        if(!rst) begin
            //Resetting Write Synchronisation Pointers
            wrptr_sync1 <= 0;
            wrptr_sync2 <= 0;
        end
        else begin
            //Write Pointer Synchronisation
            wrptr_sync1 <= wrptr_grey;
            wrptr_sync2 <= wrptr_sync1;
        end
    end

    always@(posedge rclk or negedge rst) begin
        if(!rst) begin
            //Resetting Read Pointers
            rdptr_bin <= 0;
            rdptr_grey <= 0;
        end
        else if(rdvalid) begin
            //Read Pointer Updation
            rdptr_bin <= rdptr_bin_next;
            rdptr_grey <= rdptr_grey_next;
        end
    end

    always @(posedge rclk) begin
        if (rdvalid) begin
            //Data Read
            datOut <= mem[rdptr_bin[pSize-1:0]];
        end
    end

    always@(posedge rclk or negedge rst) begin
        if(!rst) begin
            //Resetting Empty Flag
            empty <= 1;
        end
        else begin
            //Empty Flag Updation
            empty <= (rdptr_grey_next == wrptr_sync2);
        end
    end
    

//Write Clock Behaviour
    always@(posedge wclk or negedge rst) begin
        if(!rst) begin
            //Resetting Read Synchronisation Pointers
            rdptr_sync1 <= 0;
            rdptr_sync2 <= 0;
        end
        else begin
            //Read Pointer Synchronisation
            rdptr_sync1 <= rdptr_grey;
            rdptr_sync2 <= rdptr_sync1;
        end
    end

    always@(posedge wclk or negedge rst) begin
        if(!rst) begin
            //Resetting Write Pointers
            wrptr_bin <= 0;
            wrptr_grey <= 0;
        end
        else if(wrvalid) begin
            //Write Pointer Updation
            wrptr_bin <= wrptr_bin_next;
            wrptr_grey <= wrptr_grey_next;
        end
    end

    always@(posedge wclk) begin
        if(wrvalid) begin
            //Data Write
            mem[wrptr_bin[pSize-1:0]] <= datIn;
        end
    end

    always@(posedge wclk or negedge rst) begin
        if(!rst) begin
            //Resetting Full Flag
            full <= 0;
        end
        else begin
            //Full Flag Updation
            full <= (wrptr_grey_next == {~rdptr_sync2[pSize:pSize-1], rdptr_sync2[pSize-2:0]});
        end
    end

endmodule

FIFO_tb.v
`timescale 1ns/1ps
`include "FIFO_SynthesisOptimised.v"

module FIFO_tb;

    localparam WIDTH  = 16;
    localparam HEIGHT = 16;

    reg                 rst;
    reg                 wclk;
    reg                 rclk;
    reg                 wEn;
    reg                 rEn;
    reg  [WIDTH-1:0]    datIn;

    wire [WIDTH-1:0]    datOut;
    wire                empty;
    wire                full;

    //Instantiate the DUT
    FIFO #(
        .WIDTH  (WIDTH),
        .HEIGHT (HEIGHT)
    ) dut (
        .rst    (rst),
        .rclk   (rclk),
        .wclk   (wclk),
        .wEn    (wEn),
        .rEn    (rEn),
        .datIn  (datIn),
        .datOut (datOut),
        .empty  (empty),
        .full   (full)
    );

    //Clock Generation
    initial begin
        wclk = 0;
        forever #5 wclk = ~wclk;
    end

    initial begin
        rclk = 0;
        forever #10 rclk = ~rclk; 
    end

    //Print buffer contents in a clean, single-line format

    task display_buffer(input [8*8-1:0] trigger_event);
        integer i;
        begin
            $write("[%0t ps | Trigger: %s] wptr:%0d rdptr:%0d | F:%b E:%b | MEM: [ ",
                   $time, trigger_event, dut.wrptr_bin, dut.rdptr_bin, full, empty);
            for (i = 0; i < HEIGHT; i = i + 1) begin
                $write("%04h ", dut.mem[i]);
            end
            $write("]\n");
        end
    endtask

    //Triggered on posedge of EITHER wclk or rclk
    initial begin
        //Wait until out of initial reset so we don't spam during initialisation
        @(posedge rst);
        forever begin
            @(posedge wclk or posedge rclk);
            // #1 delta delay allows non-blocking register updates to settle
            #1;
            if (wclk && rclk)
                display_buffer("BOTH_CLK");
            else if (wclk)
                display_buffer("WCLK_EDGE");
            else
                display_buffer("RCLK_EDGE");
        end
    end

    //Main Test Stimulus
    initial begin
        $dumpfile("fifo_concurrent_dump.vcd");
        $dumpvars(0, FIFO_tb);

        // Signal initialisation
        wEn   = 1'b0;
        rEn   = 1'b0;
        datIn = {WIDTH{1'b0}};
        rst   = 1'b0; //Assert active-low reset

        #40;
        @(negedge wclk);
        rst   = 1'b1; //Deassert reset

        //Concurrently run producer (writes) and consumer (reads)
        fork
            //Write Process (Producer)
            begin
                repeat (30) begin
                    @(posedge wclk);
                    if (!full) begin
                        wEn   <= 1'b1;
                        datIn <= $urandom_range(16'h1000, 16'hFFFF);
                    end else begin
                        wEn   <= 1'b0; // Stall on full
                    end
                end
                @(posedge wclk);
                wEn <= 1'b0;
            end

            //Read Process (Consumer)
            begin
                //Let a few items enter the buffer first
                repeat (3) @(posedge rclk);

                repeat (30) begin
                    @(posedge rclk);
                    if (!empty) begin
                        rEn <= 1'b1;
                    end else begin
                        rEn <= 1'b0; //Stall on empty
                    end
                end
                @(posedge rclk);
                rEn <= 1'b0;
            end
        join

        //Drain any remaining words
        $display("\n--- Draining any remaining entries ---");
        while (!empty) begin
            @(posedge rclk);
            rEn <= 1'b1;
            @(posedge rclk);
            rEn <= 1'b0;
        end

        #100;
        $display("\nSimulation Complete.");
        $finish;
    end

endmodule

fifo_concurrent_dump.vcd
$date
	Sun Sep 20 21:44:43 2026
$end
$version
	Icarus Verilog
$end
$timescale
	1ps
$end
$scope module FIFO_tb $end
$var wire 1 ! full $end
$var wire 1 " empty $end
$var wire 16 # datOut [15:0] $end
$var parameter 32 $ HEIGHT $end
$var parameter 32 % WIDTH $end
$var reg 16 & datIn [15:0] $end
$var reg 1 ' rEn $end
$var reg 1 ( rclk $end
$var reg 1 ) rst $end
$var reg 1 * wEn $end
$var reg 1 + wclk $end
$scope module dut $end
$var wire 16 , datIn [15:0] $end
$var wire 1 ' rEn $end
$var wire 1 ( rclk $end
$var wire 5 - rdptr_grey_next [4:0] $end
$var wire 1 . rdvalid $end
$var wire 1 ) rst $end
$var wire 1 * wEn $end
$var wire 1 + wclk $end
$var wire 5 / wrptr_grey_next [4:0] $end
$var wire 1 0 wrvalid $end
$var wire 5 1 wrptr_bin_next [4:0] $end
$var wire 5 2 rdptr_bin_next [4:0] $end
$var parameter 32 3 HEIGHT $end
$var parameter 32 4 WIDTH $end
$var parameter 32 5 pSize $end
$var reg 16 6 datOut [15:0] $end
$var reg 1 " empty $end
$var reg 1 ! full $end
$var reg 5 7 rdptr_bin [4:0] $end
$var reg 5 8 rdptr_grey [4:0] $end
$var reg 5 9 rdptr_sync1 [4:0] $end
$var reg 5 : rdptr_sync2 [4:0] $end
$var reg 5 ; wrptr_bin [4:0] $end
$var reg 5 < wrptr_grey [4:0] $end
$var reg 5 = wrptr_sync1 [4:0] $end
$var reg 5 > wrptr_sync2 [4:0] $end
$upscope $end
$scope task display_buffer $end
$var reg 64 ? trigger_event [63:0] $end
$var integer 32 @ i [31:0] $end
$upscope $end
$upscope $end
$enddefinitions $end
$comment Show the parameter values. $end
$dumpall
b100 5
b10000 4
b10000 3
b10000 %
b10000 $
$end
#0
$dumpvars
bx @
bx ?
b0 >
b0 =
b0 <
b0 ;
b0 :
b0 9
b0 8
b0 7
bx 6
b0 2
b0 1
00
b0 /
0.
b0 -
b0 ,
0+
0*
0)
0(
0'
b0 &
bx #
1"
0!
$end
#5000
1+
#10000
0+
1(
#15000
1+
#20000
0+
0(
#25000
1+
#30000
0+
1(
#35000
1+
#40000
1)
0+
0(
#45000
b1 /
b1 1
10
b1001100011110011 &
b1001100011110011 ,
1*
1+
#46000
b10000 @
b100001101001100010010110101111101000101010001000100011101000101 ?
#50000
0+
1(
#51000
b10000 @
#55000
b11 /
b1 <
b10 1
b1 ;
b100110010000000 &
b100110010000000 ,
1+
#56000
b10000 @
b100001001001111010101000100100001011111010000110100110001001011 ?
#60000
0+
0(
#65000
b10 /
b11 <
b11 1
b10 ;
b1010000111100 &
b1010000111100 ,
1+
#66000
b10000 @
b100001101001100010010110101111101000101010001000100011101000101 ?
#70000
b11 =
0+
1(
#71000
b10000 @
#75000
b110 /
b10 <
b100 1
b11 ;
b11111011010001 &
b11111011010001 ,
1+
#76000
b10000 @
b100001001001111010101000100100001011111010000110100110001001011 ?
#80000
0+
0(
#85000
b111 /
b110 <
b101 1
b100 ;
b1000111001001101 &
b1000111001001101 ,
1+
#86000
b10000 @
b100001101001100010010110101111101000101010001000100011101000101 ?
#90000
b11 >
b110 =
0+
1(
#91000
b10000 @
#95000
b101 /
b111 <
b110 1
b101 ;
b1100101001110001 &
b1100101001110001 ,
1+
#96000
b10000 @
b100001001001111010101000100100001011111010000110100110001001011 ?
#100000
0+
0(
#105000
b100 /
b101 <
b111 1
b110 ;
b11111110010110 &
b11111110010110 ,
1+
#106000
b10000 @
b100001101001100010010110101111101000101010001000100011101000101 ?
#110000
b110 >
b101 =
0"
0+
1(
#111000
b10000 @
#115000
b1100 /
b100 <
b1000 1
b111 ;
b1100010100011 &
b1100010100011 ,
1+
#116000
b10000 @
b100001001001111010101000100100001011111010000110100110001001011 ?
#120000
0+
0(
#125000
b1101 /
b1100 <
b1001 1
b1000 ;
b1000100011100100 &
b1000100011100100 ,
1+
#126000
b10000 @
b100001101001100010010110101111101000101010001000100011101000101 ?
#130000
b1 -
b1 2
1.
b101 >
b1100 =
1'
0+
1(
#131000
b10000 @
#135000
b1111 /
b1101 <
b1010 1
b1001 ;
b1000111001101010 &
b1000111001101010 ,
1+
#136000
b10000 @
b100001001001111010101000100100001011111010000110100110001001011 ?
#140000
0+
0(
#145000
b1110 /
b1111 <
b1011 1
b1010 ;
b1011111101110001 &
b1011111101110001 ,
1+
#146000
b10000 @
b100001101001100010010110101111101000101010001000100011101000101 ?
#150000
b11 -
b1100 >
b1111 =
b1 8
b10 2
b1 7
b1001100011110011 #
b1001100011110011 6
0+
1(
#151000
b10000 @
#155000
b1010 /
b1 9
b1110 <
b1100 1
b1011 ;
b1010010010100100 &
b1010010010100100 ,
1+
#156000
b10000 @
b100001001001111010101000100100001011111010000110100110001001011 ?
#160000
0+
0(
#165000
b1011 /
b1010 <
b1101 1
b1100 ;
b1 :
b1111011101100111 &
b1111011101100111 ,
1+
#166000
b10000 @
b100001101001100010010110101111101000101010001000100011101000101 ?
#170000
b10 -
b11 8
b11 2
b10 7
b1111 >
b1010 =
b100110010000000 #
b100110010000000 6
0+
1(
#171000
b10000 @
#175000
b1001 /
b11 9
b1011 <
b1110 1
b1101 ;
b1100100111001011 &
b1100100111001011 ,
1+
#176000
b10000 @
b100001001001111010101000100100001011111010000110100110001001011 ?
#180000
0+
0(
#185000
b1000 /
b1001 <
b1111 1
b1110 ;
b11 :
b1111110100101110 &
b1111110100101110 ,
1+
#186000
b10000 @
b100001101001100010010110101111101000101010001000100011101000101 ?
#190000
b110 -
b1010 >
b1001 =
b10 8
b100 2
b11 7
b1010000111100 #
b1010000111100 6
0+
1(
#191000
b10000 @
#195000
b11000 /
b10 9
b1000 <
b10000 1
b1111 ;
b110110100000011 &
b110110100000011 ,
1+
#196000
b10000 @
b100001001001111010101000100100001011111010000110100110001001011 ?
#200000
0+
0(
#205000
b11001 /
b11000 <
b10001 1
b10000 ;
b10 :
b110110011001000 &
b110110011001000 ,
1+
#206000
b10000 @
b100001101001100010010110101111101000101010001000100011101000101 ?
#210000
b111 -
b110 8
b101 2
b100 7
b1001 >
b11000 =
b11111011010001 #
b11111011010001 6
0+
1(
#211000
b10000 @
#215000
b11011 /
b110 9
b11001 <
b10010 1
b10001 ;
b101111111000010 &
b101111111000010 ,
1+
#216000
b10000 @
b100001001001111010101000100100001011111010000110100110001001011 ?
#220000
0+
0(
#225000
b11010 /
b11011 <
b10011 1
b10010 ;
b110 :
b1111001110000100 &
b1111001110000100 ,
1+
#226000
b10000 @
b100001101001100010010110101111101000101010001000100011101000101 ?
#230000
b101 -
b11000 >
b11011 =
b111 8
b110 2
b101 7
b1000111001001101 #
b1000111001001101 6
0+
1(
#231000
b10000 @
#235000
b11110 /
b111 9
b11010 <
b10100 1
b10011 ;
b100100000010101 &
b100100000010101 ,
1+
#236000
b10000 @
b100001001001111010101000100100001011111010000110100110001001011 ?
#240000
0+
0(
#245000
00
b11110 /
1!
b11110 <
b10100 1
b10100 ;
b111 :
b1100010011111 &
b1100010011111 ,
1+
#246000
b10000 @
b100001101001100010010110101111101000101010001000100011101000101 ?
#250000
b100 -
b101 8
b111 2
b110 7
b11011 >
b11110 =
b1100101001110001 #
b1100101001110001 6
0+
1(
#251000
b10000 @
#255000
b101 9
0!
0*
1+
#256000
b10000 @
b100001001001111010101000100100001011111010000110100110001001011 ?
#260000
0+
0(
#265000
b11111 /
b10101 1
10
b101 :
b1100101101101110 &
b1100101101101110 ,
1*
1+
#266000
b10000 @
b100001101001100010010110101111101000101010001000100011101000101 ?
#270000
b1100 -
b11110 >
b100 8
b1000 2
b111 7
b11111110010110 #
b11111110010110 6
0+
1(
#271000
b10000 @
#275000
b11101 /
b100 9
b11111 <
b10110 1
b10101 ;
b1111100110011101 &
b1111100110011101 ,
1+
#276000
b10000 @
b100001001001111010101000100100001011111010000110100110001001011 ?
#280000
0+
0(
#285000
00
b11101 /
1!
b11101 <
b10110 1
b10110 ;
b100 :
b111000011111111 &
b111000011111111 ,
1+
#286000
b10000 @
b100001101001100010010110101111101000101010001000100011101000101 ?
#290000
b1101 -
b1100 8
b1001 2
b1000 7
b11101 =
b1100010100011 #
b1100010100011 6
0+
1(
#291000
b10000 @
#295000
b1100 9
0!
0*
1+
#296000
b10000 @
b100001001001111010101000100100001011111010000110100110001001011 ?
#300000
0+
0(
#305000
b11100 /
b10111 1
10
b1100 :
b111110011000000 &
b111110011000000 ,
1*
1+
#306000
b10000 @
b100001101001100010010110101111101000101010001000100011101000101 ?
#310000
b1111 -
b11101 >
b1101 8
b1010 2
b1001 7
b1000100011100100 #
b1000100011100100 6
0+
1(
#311000
b10000 @
#315000
b10100 /
b1101 9
b11100 <
b11000 1
b10111 ;
b110110010011101 &
b110110010011101 ,
1+
#316000
b10000 @
b100001001001111010101000100100001011111010000110100110001001011 ?
#320000
0+
0(
#325000
00
b10100 /
1!
b10100 <
b11000 1
b11000 ;
b1101 :
b1011001101110010 &
b1011001101110010 ,
1+
#326000
b10000 @
b100001101001100010010110101111101000101010001000100011101000101 ?
#330000
b1110 -
b1111 8
b1011 2
b1010 7
b10100 =
b1000111001101010 #
b1000111001101010 6
0+
1(
#331000
b10000 @
#335000
b1111 9
0!
0*
1+
#336000
b10000 @
b100001001001111010101000100100001011111010000110100110001001011 ?
#340000
0+
0(
#345000
b1111 :
1+
#346000
b10000 @
b100001101001100010010110101111101000101010001000100011101000101 ?
#350000
b1010 -
b10100 >
b1110 8
b1100 2
b1011 7
b1011111101110001 #
b1011111101110001 6
0+
1(
#351000
b10000 @
#355000
b1110 9
1+
#356000
b10000 @
b100001001001111010101000100100001011111010000110100110001001011 ?
#360000
0+
0(
#365000
b1110 :
1+
#366000
b10000 @
b100001101001100010010110101111101000101010001000100011101000101 ?
#370000
b1011 -
b1010 8
b1101 2
b1100 7
b1010010010100100 #
b1010010010100100 6
0+
1(
#371000
b10000 @
#375000
b1010 9
1+
#376000
b10000 @
b100001001001111010101000100100001011111010000110100110001001011 ?
#380000
0+
0(
#385000
b1010 :
1+
#386000
b10000 @
b100001101001100010010110101111101000101010001000100011101000101 ?
#390000
b1001 -
b1011 8
b1110 2
b1101 7
b1111011101100111 #
b1111011101100111 6
0+
1(
#391000
b10000 @
#395000
b1011 9
1+
#396000
b10000 @
b100001001001111010101000100100001011111010000110100110001001011 ?
#400000
0+
0(
#405000
b1011 :
1+
#406000
b10000 @
b100001101001100010010110101111101000101010001000100011101000101 ?
#410000
b1000 -
b1001 8
b1111 2
b1110 7
b1100100111001011 #
b1100100111001011 6
0+
1(
#411000
b10000 @
#415000
b1001 9
1+
#416000
b10000 @
b100001001001111010101000100100001011111010000110100110001001011 ?
#420000
0+
0(
#425000
b1001 :
1+
#426000
b10000 @
b100001101001100010010110101111101000101010001000100011101000101 ?
#430000
b11000 -
b1000 8
b10000 2
b1111 7
b1111110100101110 #
b1111110100101110 6
0+
1(
#431000
b10000 @
#435000
b1000 9
1+
#436000
b10000 @
b100001001001111010101000100100001011111010000110100110001001011 ?
#440000
0+
0(
#445000
b1000 :
1+
#446000
b10000 @
b100001101001100010010110101111101000101010001000100011101000101 ?
#450000
b11001 -
b11000 8
b10001 2
b10000 7
b110110100000011 #
b110110100000011 6
0+
1(
#451000
b10000 @
#455000
b11000 9
1+
#456000
b10000 @
b100001001001111010101000100100001011111010000110100110001001011 ?
#460000
0+
0(
#465000
b11000 :
1+
#466000
b10000 @
b100001101001100010010110101111101000101010001000100011101000101 ?
#470000
b11011 -
b11001 8
b10010 2
b10001 7
b110110011001000 #
b110110011001000 6
0+
1(
#471000
b10000 @
#475000
b11001 9
1+
#476000
b10000 @
b100001001001111010101000100100001011111010000110100110001001011 ?
#480000
0+
0(
#485000
b11001 :
1+
#486000
b10000 @
b100001101001100010010110101111101000101010001000100011101000101 ?
#490000
b11010 -
b11011 8
b10011 2
b10010 7
b101111111000010 #
b101111111000010 6
0+
1(
#491000
b10000 @
#495000
b11011 9
1+
#496000
b10000 @
b100001001001111010101000100100001011111010000110100110001001011 ?
#500000
0+
0(
#505000
b11011 :
1+
#506000
b10000 @
b100001101001100010010110101111101000101010001000100011101000101 ?
#510000
b11110 -
b11010 8
b10100 2
b10011 7
b1111001110000100 #
b1111001110000100 6
0+
1(
#511000
b10000 @
#515000
b11010 9
1+
#516000
b10000 @
b100001001001111010101000100100001011111010000110100110001001011 ?
#520000
0+
0(
#525000
b11010 :
1+
#526000
b10000 @
b100001101001100010010110101111101000101010001000100011101000101 ?
#530000
b11111 -
b11110 8
b10101 2
b10100 7
b100100000010101 #
b100100000010101 6
0+
1(
#531000
b10000 @
#535000
b11110 9
1+
#536000
b10000 @
b100001001001111010101000100100001011111010000110100110001001011 ?
#540000
0+
0(
#545000
b11110 :
1+
#546000
b10000 @
b100001101001100010010110101111101000101010001000100011101000101 ?
#550000
b11101 -
b11111 8
b10110 2
b10101 7
b1100101101101110 #
b1100101101101110 6
0+
1(
#551000
b10000 @
#555000
b11111 9
1+
#556000
b10000 @
b100001001001111010101000100100001011111010000110100110001001011 ?
#560000
0+
0(
#565000
b11111 :
1+
#566000
b10000 @
b100001101001100010010110101111101000101010001000100011101000101 ?
#570000
b11100 -
b11101 8
b10111 2
b10110 7
b1111100110011101 #
b1111100110011101 6
0+
1(
#571000
b10000 @
#575000
b11101 9
1+
#576000
b10000 @
b100001001001111010101000100100001011111010000110100110001001011 ?
#580000
0+
0(
#585000
b11101 :
1+
#586000
b10000 @
b100001101001100010010110101111101000101010001000100011101000101 ?
#590000
b10100 -
b11100 8
b11000 2
b10111 7
b111110011000000 #
b111110011000000 6
0+
1(
#591000
b10000 @
#595000
b11100 9
1+
#596000
b10000 @
b100001001001111010101000100100001011111010000110100110001001011 ?
#600000
0+
0(
#605000
b11100 :
1+
#606000
b10000 @
b100001101001100010010110101111101000101010001000100011101000101 ?
#610000
0.
b10100 -
1"
b10100 8
b11000 2
b11000 7
b110110010011101 #
b110110010011101 6
0+
1(
#611000
b10000 @
#615000
b10100 9
1+
#616000
b10000 @
b100001001001111010101000100100001011111010000110100110001001011 ?
#620000
0+
0(
#625000
b10100 :
1+
#626000
b10000 @
b100001101001100010010110101111101000101010001000100011101000101 ?
#630000
0'
0+
1(
#631000
b10000 @
#635000
1+
#636000
b10000 @
b100001001001111010101000100100001011111010000110100110001001011 ?
#640000
0+
0(
#645000
1+
#646000
b10000 @
b100001101001100010010110101111101000101010001000100011101000101 ?
#650000
0+
1(
#651000
b10000 @
#655000
1+
#656000
b10000 @
b100001001001111010101000100100001011111010000110100110001001011 ?
#660000
0+
0(
#665000
1+
#666000
b10000 @
b100001101001100010010110101111101000101010001000100011101000101 ?
#670000
0+
1(
#671000
b10000 @
#675000
1+
#676000
b10000 @
b100001001001111010101000100100001011111010000110100110001001011 ?
#680000
0+
0(
#685000
1+
#686000
b10000 @
b100001101001100010010110101111101000101010001000100011101000101 ?
#690000
0+
1(
#691000
b10000 @
#695000
1+
#696000
b10000 @
b100001001001111010101000100100001011111010000110100110001001011 ?
#700000
0+
0(
#705000
1+
#706000
b10000 @
b100001101001100010010110101111101000101010001000100011101000101 ?
#710000
0+
1(
#711000
b10000 @
#715000
1+
#716000
b10000 @
b100001001001111010101000100100001011111010000110100110001001011 ?
#720000
0+
0(
#725000
1+
#726000
b10000 @
b100001101001100010010110101111101000101010001000100011101000101 ?
#730000
0+
1(
#731000
b10000 @
#735000
1+
#736000
b10000 @
b100001001001111010101000100100001011111010000110100110001001011 ?
#740000
0+
0(
#745000
1+
#746000
b10000 @
b100001101001100010010110101111101000101010001000100011101000101 ?
#750000
0+
1(
#751000
b10000 @
#755000
1+
#756000
b10000 @
b100001001001111010101000100100001011111010000110100110001001011 ?
#760000
0+
0(
#765000
1+
#766000
b10000 @
b100001101001100010010110101111101000101010001000100011101000101 ?
#770000
0+
1(
#771000
b10000 @
#775000
1+
#776000
b10000 @
b100001001001111010101000100100001011111010000110100110001001011 ?
#780000
0+
0(
#785000
1+
#786000
b10000 @
b100001101001100010010110101111101000101010001000100011101000101 ?
#790000
0+
1(
#791000
b10000 @
#795000
1+
#796000
b10000 @
b100001001001111010101000100100001011111010000110100110001001011 ?
#800000
0+
0(
#805000
1+
#806000
b10000 @
b100001101001100010010110101111101000101010001000100011101000101 ?
